simopt.py
simopt-0.4.0.dist-info/LICENSE
simopt-0.4.0.dist-info/METADATA
simopt-0.4.0.dist-info/WHEEL
simopt-0.4.0.dist-info/top_level.txt
simopt-0.4.0.dist-info/RECORD
