Metadata-Version: 2.1
Name: simopt
Version: 0.4.0
Summary: SIMple OPTion parser
Home-page: http://github.com/Tsjerk/simopt
Download-URL: https://github.com/Tsjerk/simopt/archive/v0.1.tar.gz
Author: Tsjerk A. Wassenaar
Author-email: tsjerkw@gmail.com
License: MIT
Keywords: simple option parser
Classifier: Development Status :: 3 - Alpha
Classifier: License :: OSI Approved :: MIT License
Classifier: Programming Language :: Python
License-File: LICENSE
